{
  "task_type": "implement",
  "task_id": "921",
  "started_at": "2026-02-16T17:55:28",
  "finished_at": "2026-02-16T18:09:16",
  "attempts": [
    {
      "agent": "codex",
      "task": "implement #921",
      "success": true,
      "result": null,
      "raw_output": "",
      "errors": null,
      "files_modified": [],
      "build_result": "OK",
      "test_result": "OK",
      "timed_out": false,
      "diff_summary": null,
      "timestamp": "2026-02-16T18:09:16"
    }
  ],
  "timeout_count": 0,
  "all_timed_out": false,
  "final_success": true
}
