{
  "number": 351,
  "repo": "mRemoteNG/mRemoteNG",
  "title": "Dynamic tab name",
  "state": "open",
  "labels": [
    "Enhancement"
  ],
  "author": "cwi-ezoutas",
  "created_at": "2017-01-18T15:01:11Z",
  "github_updated_at": "2026-02-20T13:39:12Z",
  "body_snippet": "It would be very useful to have dynamic tab naming for ssh connections.\r\nExample:\r\n1) Connect to \"Server A\" as user \"testor\" where hostname is \"servera\"\r\n2) Tab should be named \"testor@servera (Server A)\"\r\n3) SSH from \"Server A\" to another server at IP 192.168.1.2 with user \"test\"\r\n4) Tab should be named \"test@192.168.1.2 (Server A)\"\r\n\r\nThis is extremely useful when you manage hundred of servers.\r\nThis is the same with:\r\nhttps://mremoteng.atlassian.net/browse/MR-571\r\n\r\nCould not find the same ti...",
  "our_status": "testing",
  "priority": "P3-enhancement",
  "target_release": null,
  "our_branch": null,
  "our_pr": null,
  "iterations": [
    {
      "seq": 1,
      "date": "2026-02-15",
      "type": "triaged",
      "description": "Feature request to dynamically update tab titles to reflect the remote session's window title (e.g., PuTTY progress), improving usability for multi-session workflows"
    },
    {
      "seq": 2,
      "date": "2026-02-15",
      "type": "testing",
      "description": "Fix in b84d21b1"
    }
  ],
  "comments": [
    {
      "id": "MDEyOklzc3VlQ29tbWVudDI3MzQ5OTU0Nw==",
      "author": "sparerd",
      "date": "2017-01-18T15:04:48Z",
      "snippet": "Step 4 is currently not possible without significantly changing PuTTY.\r\n\r\nWe may be able to look into this once PuTTY is replaced by SSH.Net (#181)",
      "is_ours": false,
      "analyzed": false,
      "action_needed": true
    },
    {
      "id": "MDEyOklzc3VlQ29tbWVudDI3MzUwMDUxNQ==",
      "author": "cwi-ezoutas",
      "date": "2017-01-18T15:08:05Z",
      "snippet": "I don't know if it helps, but SuperPutty does that with the original Putty in it's backend.",
      "is_ours": false,
      "analyzed": false,
      "action_needed": true
    },
    {
      "id": "MDEyOklzc3VlQ29tbWVudDI3MzUwMDc1MA==",
      "author": "sparerd",
      "date": "2017-01-18T15:08:50Z",
      "snippet": "We can take a look and see how they did it - thanks for the tip.",
      "is_ours": false,
      "analyzed": false,
      "action_needed": true
    },
    {
      "id": "MDEyOklzc3VlQ29tbWVudDI3MzUxMTE2Mg==",
      "author": "sparerd",
      "date": "2017-01-18T15:44:10Z",
      "snippet": "Ok, I see how they did it now. I forgot that putty changes the window name automatically when the current host changes. We should be able to do this fairly easily",
      "is_ours": false,
      "analyzed": false,
      "action_needed": true
    },
    {
      "id": "MDEyOklzc3VlQ29tbWVudDQ0MDIyMTAwOA==",
      "author": "rk36912",
      "date": "2018-11-20T10:21:38Z",
      "snippet": "Hi, I have downloaded v1.76.11 and I am still not able to change the title dynamically by changing the PS1 similar to SuperPutty or Putty. Is this feature available in mRemoteNg? I really like to use mRemoteNG.",
      "is_ours": false,
      "analyzed": false,
      "action_needed": true
    },
    {
      "id": "MDEyOklzc3VlQ29tbWVudDQ0MDI3OTQ2NA==",
      "author": "sparerd",
      "date": "2018-11-20T13:49:12Z",
      "snippet": "This feature is being developed for v1.77",
      "is_ours": false,
      "analyzed": false,
      "action_needed": true
    },
    {
      "id": "MDEyOklzc3VlQ29tbWVudDQ0ODY3MzIzMA==",
      "author": "Ishayahu",
      "date": "2018-12-19T17:13:08Z",
      "snippet": "It will be great to see all changes in putty winodw name, for example when I use portmaseter on freebsd to upgrade my ports, with putty I can see at which step it is at the moment (5/9 i.e. 5 done, 9 total)",
      "is_ours": false,
      "analyzed": false,
      "action_needed": true
    },
    {
      "id": "MDEyOklzc3VlQ29tbWVudDczMzAwOTcxMw==",
      "author": "zsbolyoczki",
      "date": "2020-11-24T14:29:16Z",
      "snippet": "Hi, \r\n\r\nAny progress on this? 1.77 is still in prerelease since , Apr 29, 2019\r\nCan you pls backport this feature to 1.76?\r\n\r\nThanks.\r\n\r\n ",
      "is_ours": false,
      "analyzed": false,
      "action_needed": true
    },
    {
      "id": "IC_kwDOAAcIMM5Ucp6k",
      "author": "Kvarkas",
      "date": "2023-02-04T16:46:33Z",
      "snippet": "hello, unfortunately we are moving forward and its a lot of changes in 1.77.x version including .Net 6 framework... so please wait for a new stable release of 1.77",
      "is_ours": false,
      "analyzed": false,
      "action_needed": true
    }
  ],
  "comments_cursor": "2026-02-20T13:39:12Z",
  "unread_comments": 9,
  "needs_action": true,
  "waiting_for_us": true,
  "last_synced": "2026-02-21T06:14:50Z",
  "notes": "AI triage: Feature request to dynamically update tab titles to reflect the remote session's window title (e.g., PuTTY progress), improving usability for multi-session workflows\nApproach: Subscribe to the embedded process/control window title changes (via WinEvents or polling NativeWindow text) and propagate updates to the tab header, with an opt-in setting in ConnectionInfo to enable dynamic tab naming"
}
